{
	"name": "smallLang-spec-theme",
	"type": "dark",
	"tokenColors": [
		{
			"name": "Comment",
			"scope": [
				"comment",
				"punctuation.definition.comment"
			],
			"settings": {
				"fontStyle": "italic",
				"foreground": "#546E7A"
			}
		},
		{
			"name": "parentesis",
			"scope": [
				"parenthesis",
				"punctuation.parenthesis"
			],
			"settings": {
				"fontStyle": "bold",
				"foreground": "#df7e8a"
			}
		},
		{
			"name": "especificacion",
			"scope": [
				"keywords.especificacion"
			],
			"settings": {
				"fontStyle": "italic",
				"foreground": "#d73d6c"
			}
		},
		{
			"name": "especificacion.types",
			"scope": [
				"keywords.especificacion.types"
			],
			"settings": {
				"fontStyle": "italic",
				"foreground": "#f4d75e"
			}
		},
		{
			"name": "keywords.especificacion.io",
			"scope": [
				"keywords.especificacion.io"
			],
			"settings": {
				"fontStyle": "regular",
				"foreground": "#65b2c6"
			}
		},
		{
			"name": "smallLang",
			"scope": [
				"keywords.smallLang",
				"keywords.otros"
			],
			"settings": {
				"fontStyle": "italic",
				"foreground": "#65b2c6"
			}
		},
		{
			"name": "otros",
			"scope": [
				"keywords.otros"
			],
			"settings": {
				"fontStyle": "italic",
				"foreground": "#0077b6"
			}
		},
		{
			"name": "types.boolean",
			"scope": [
				"types.boolean"
			],
			"settings": {
				"foreground": "#2a9d8f"
			}
		},
		{
			"name": "types.number",
			"scope": [
				"types.number"
			],
			"settings": {
			}
		},
		{
			"name": "types.char",
			"scope": [
				"types.char"
			],
			"settings": {
				"foreground": "#f4a261"
			}
		},
		{
			"name": "logicalConnectors",
			"scope": [
				"logicalConnectors"
			],
			"settings": {
				"fontStyle": "regular",
				"foreground": "#F6386D"
			}
		}
	]
}
